djitellopy/__init__.py
djitellopy/enforce_types.py
djitellopy/swarm.py
djitellopy/tello.py
djitellopy-2.5.0.dist-info/LICENSE.txt
djitellopy-2.5.0.dist-info/METADATA
djitellopy-2.5.0.dist-info/WHEEL
djitellopy-2.5.0.dist-info/top_level.txt
djitellopy-2.5.0.dist-info/RECORD
