Metadata-Version: 2.1
Name: djitellopy
Version: 2.5.0
Summary: Tello drone library including support for video streaming, swarms, state packets and more
Home-page: https://github.com/damiafuentes/DJITelloPy
Download-URL: https://github.com/damiafuentes/DJITelloPy/archive/2.5.0.tar.gz
Author: Jakob Löw
Author-email: djitellopy@m4gnus.de
License: MIT
Keywords: tello,dji,drone,sdk,official sdk
Classifier: Development Status :: 5 - Production/Stable
Classifier: Intended Audience :: Developers
Classifier: Topic :: Software Development :: Build Tools
Classifier: License :: OSI Approved :: MIT License
Classifier: Programming Language :: Python :: 3.6
Classifier: Programming Language :: Python :: 3.7
Classifier: Programming Language :: Python :: 3.8
Classifier: Programming Language :: Python :: 3.9
Classifier: Programming Language :: Python :: 3.10
Classifier: Programming Language :: Python :: 3.11
Requires-Python: >=3.6
License-File: LICENSE.txt
